cbr_custom_news_feeds/__init__.py
cbr_custom_news_feeds/config/Custom_News__Shared_Constants.py
cbr_custom_news_feeds/config/__init__.py
cbr_custom_news_feeds/fast_api/News_Feeds__Fast_API.py
cbr_custom_news_feeds/fast_api/__init__.py
cbr_custom_news_feeds/fast_api/routes/Routes__Info.py
cbr_custom_news_feeds/fast_api/routes/__init__.py
cbr_custom_news_feeds/lambdas/__init__.py
cbr_custom_news_feeds/lambdas/handler.py
cbr_custom_news_feeds/news_feeds/News_Feeds__Http_Content.py
cbr_custom_news_feeds/news_feeds/__init__.py
cbr_custom_news_feeds/open_api/__init__.py
cbr_custom_news_feeds/open_api/open-api.html
cbr_custom_news_feeds/open_api/openapi.json
cbr_custom_news_feeds/providers/__init__.py
cbr_custom_news_feeds/providers/cyber_security/__init__.py
cbr_custom_news_feeds/providers/cyber_security/__to_create_integration/notes.txt
cbr_custom_news_feeds/providers/cyber_security/__to_create_integration/reddit/notes.txt
cbr_custom_news_feeds/providers/cyber_security/__to_create_integration/the_stack/notes.txt
cbr_custom_news_feeds/providers/cyber_security/hacker_news/Hacker_News__Files.py
cbr_custom_news_feeds/providers/cyber_security/hacker_news/Hacker_News__Http_Content.py
cbr_custom_news_feeds/providers/cyber_security/hacker_news/Hacker_News__Parser.py
cbr_custom_news_feeds/providers/cyber_security/hacker_news/Hacker_News__Prompt_Creator.py
cbr_custom_news_feeds/providers/cyber_security/hacker_news/Hacker_News__S3_DB.py
cbr_custom_news_feeds/providers/cyber_security/hacker_news/Hacker_News__S3__Key_Generator.py
cbr_custom_news_feeds/providers/cyber_security/hacker_news/__init__.py
cbr_custom_news_feeds/providers/cyber_security/hacker_news/models/Model__Hacker_News__Article.py
cbr_custom_news_feeds/providers/cyber_security/hacker_news/models/Model__Hacker_News__Data__Feed.py
cbr_custom_news_feeds/providers/cyber_security/hacker_news/models/Model__Hacker_News__Feed.py
cbr_custom_news_feeds-1.10.0.dist-info/LICENSE
cbr_custom_news_feeds-1.10.0.dist-info/METADATA
cbr_custom_news_feeds-1.10.0.dist-info/WHEEL
cbr_custom_news_feeds-1.10.0.dist-info/RECORD
